pvcurve/__init__.py
pvcurve/core.py
pvcurve-0.1.0.dist-info/licenses/LICENSE
pvcurve-0.1.0.dist-info/METADATA
pvcurve-0.1.0.dist-info/WHEEL
pvcurve-0.1.0.dist-info/top_level.txt
pvcurve-0.1.0.dist-info/RECORD
