Metadata-Version: 2.4
Name: pvcurve
Version: 0.1.0
Summary: Tools for analyzing pressure–volume curves in plant physiology
Author: Jean Allen
License: MIT
Project-URL: Homepage, https://github.com/jean-allen/pvcurve
Project-URL: Issues, https://github.com/jean-allen/pvcurve/issues
Requires-Python: >=3.6
License-File: LICENSE
Requires-Dist: numpy
Requires-Dist: pandas
Requires-Dist: statsmodels
Requires-Dist: matplotlib
Requires-Dist: openpyxl
Dynamic: license-file
